{"learner":{"attributes":{"best_iteration":"99","best_ntree_limit":"100","scikit_learn":"{\"use_label_encoder\": false, \"n_estimators\": 100, \"objective\": \"binary:logistic\", \"max_depth\": 4, \"max_leaves\": 0, \"max_bin\": 256, \"grow_policy\": \"depthwise\", \"learning_rate\": 0.05, \"verbosity\": null, \"booster\": \"gbtree\", \"tree_method\": \"exact\", \"gamma\": 0, \"min_child_weight\": 11, \"max_delta_step\": 0, \"subsample\": 0.8, \"sampling_method\": \"uniform\", \"colsample_bytree\": 0.7, \"colsample_bylevel\": 1, \"colsample_bynode\": 1, \"reg_alpha\": 0, \"reg_lambda\": 1, \"scale_pos_weight\": 1, \"base_score\": 0.5, \"missing\": NaN, \"num_parallel_tree\": 1, \"random_state\": 42, \"n_jobs\": 0, \"monotone_constraints\": \"()\", \"interaction_constraints\": \"\", \"importance_type\": null, \"gpu_id\": -1, \"validate_parameters\": 1, \"predictor\": \"auto\", \"enable_categorical\": false, \"max_cat_to_onehot\": 4, \"eval_metric\": null, \"early_stopping_rounds\": null, \"callbacks\": null, \"classes_\": [0, 1], \"n_classes_\": 2, \"_estimator_type\": \"classifier\"}"},"feature_names":["Time","V1","V2","V3","V4","V5","V6","V7","V8","V9","V10","V11","V12","V13","V14","V15","V16","V17","V18","V19","V20","V21","V22","V23","V24","V25","V26","V27","V28","Amount"],"feature_types":["float","float","float","float","float","float","float","float","float","float","float","float","float","float","float","float","float","float","float","float","float","float","float","float","float","float","float","float","float","float"],"gradient_booster":{"model":{"gbtree_model_param":{"num_parallel_tree":"1","num_trees":"100","size_leaf_vector":"0"},"tree_info":[0,0,0,0,0,0,0,0,0,0,0,0,0,0,0,0,0,0,0,0,0,0,0,0,0,0,0,0,0,0,0,0,0,0,0,0,0,0,0,0,0,0,0,0,0,0,0,0,0,0,0,0,0,0,0,0,0,0,0,0,0,0,0,0,0,0,0,0,0,0,0,0,0,0,0,0,0,0,0,0,0,0,0,0,0,0,0,0,0,0,0,0,0,0,0,0,0,0,0,0],"trees":[{"base_weights":[-1.724138E-1,-1.9747634E0,1.9700375E0],"categories":[],"categories_nodes":[],"categories_segments":[],"categories_sizes":[],"default_left":[1,0,0],"id":0,"left_children":[1,-1,-1],"loss_changes":[5.6380005E2,0E0,0E0],"parents":[2147483647,0,0],"right_children":[2,-1,-1],"split_conditions":[-9.904898E-1,-9.873817E-2,9.8501876E-2],"split_indices":[0,0,0],"split_type":[0,0,0],"sum_hessian":[1.44E2,7.825E1,6.575E1],"tree_param":{"num_deleted":"0","num_feature":"30","num_nodes":"3","size_leaf_vector":"0"}},{"base_weights":[-1.7139527E-1,-1.8823196E0,1.8778865E0],"categories":[],"categories_nodes":[],"categories_segments":[],"categories_sizes":[],"default_left":[1,0,0],"id":1,"left_children":[1,-1,-1],"loss_changes":[5.1857263E2,0E0,0E0],"parents":[2147483647,0,0],"right_children":[2,-1,-1],"split_conditions":[-9.9010205E-1,-9.411598E-2,9.3894325E-2],"split_indices":[0,0,0],"split_type":[0,0,0],"sum_hessian":[1.4589488E2,7.955593E1,6.633895E1],"tree_param":{"num_deleted":"0","num_feature":"30","num_nodes":"3","size_leaf_vector":"0"}},{"base_weights":[-1.3208494E-1,-1.8015847E0,1.7983854E0],"categories":[],"categories_nodes":[],"categories_segments":[],"categories_sizes":[],"default_left":[1,0,0],"id":2,"left_children":[1,-1,-1],"loss_changes":[4.7666193E2,0E0,0E0],"parents":[2147483647,0,0],"right_children":[2,-1,-1],"split_conditions":[-9.666643E-1,-9.007924E-2,8.991927E-2],"split_indices":[0,0,0],"split_type":[0,0,0],"sum_hessian":[1.4589226E2,7.826997E1,6.7622284E1],"tree_param":{"num_deleted":"0","num_feature":"30","num_nodes":"3","size_leaf_vector":"0"}},{"base_weights":[-1.3787697E-1,1.5709453E0,-1.4392395E0,1.7203128E0,8.2554305E-1,-8.293086E-1,-1.5460078E0],"categories":[],"categories_nodes":[],"categories_segments":[],"categories_sizes":[],"default_left":[1,1,1,0,0,0,0],"id":3,"left_children":[1,3,5,-1,-1,-1,-1],"loss_changes":[3.113345E2,5.3229218E0,3.8898468E0,0E0,0E0,0E0,0E0],"parents":[2147483647,0,0,1,1,2,2],"right_children":[2,4,6,-1,-1,-1,-1],"split_conditions":[-1.6166106E0,-2.2598205E0,-3.1040245E-1,8.601564E-2,4.127715E-2,-4.146543E-2,-7.730039E-2],"split_indices":[14,10,8,0,0,0,0],"split_type":[0,0,0,0,0,0,0],"sum_hessian":[1.3798457E2,5.956391E1,7.842067E1,4.8531097E1,1.1032811E1,1.2988605E1,6.543207E1],"tree_param":{"num_deleted":"0","num_feature":"30","num_nodes":"7","size_leaf_vector":"0"}},{"base_weights":[-1.1004868E-1,-1.6826693E0,1.6845878E0],"categories":[],"categories_nodes":[],"categories_segments":[],"categories_sizes":[],"default_left":[1,0,0],"id":4,"left_children":[1,-1,-1],"loss_changes":[4.0604733E2,0E0,0E0],"parents":[2147483647,0,0],"right_children":[2,-1,-1],"split_conditions":[-9.904898E-1,-8.413347E-2,8.4229395E-2],"split_indices":[0,0,0],"split_type":[0,0,0],"sum_hessian":[1.418676E2,7.564398E1,6.622362E1],"tree_param":{"num_deleted":"0","num_feature":"30","num_nodes":"3","size_leaf_vector":"0"}},{"base_weights":[-1.3086857E-1,-1.6270833E0,1.6265668E0],"categories":[],"categories_nodes":[],"categories_segments":[],"categories_sizes":[],"default_left":[1,0,0],"id":5,"left_children":[1,-1,-1],"loss_changes":[3.7670477E2,0E0,0E0],"parents":[2147483647,0,0],"right_children":[2,-1,-1],"split_conditions":[-9.9010205E-1,-8.135416E-2,8.132834E-2],"split_indices":[0,0,0],"split_type":[0,0,0],"sum_hessian":[1.4125446E2,7.633762E1,6.491683E1],"tree_param":{"num_deleted":"0","num_feature":"30","num_nodes":"3","size_leaf_vector":"0"}},{"base_weights":[-1.19898275E-1,-1.5760225E0,1.5765843E0],"categories":[],"categories_nodes":[],"categories_segments":[],"categories_sizes":[],"default_left":[1,0,0],"id":6,"left_children":[1,-1,-1],"loss_changes":[3.421606E2,0E0,0E0],"parents":[2147483647,0,0],"right_children":[2,-1,-1],"split_conditions":[-9.905015E-1,-7.8801125E-2,7.882922E-2],"split_indices":[0,0,0],"split_type":[0,0,0],"sum_hessian":[1.3650449E2,7.349408E1,6.30104E1],"tree_param":{"num_deleted":"0","num_feature":"30","num_nodes":"3","size_leaf_vector":"0"}},{"base_weights":[-1.22297764E-1,1.4278169E0,-1.2277675E0,1.5116054E0,9.9193263E-1,-2.604075E-1,-1.3929173E0,-1.454651E0,-1.0119171E0],"categories":[],"categories_nodes":[],"categories_segments":[],"categories_sizes":[],"default_left":[1,1,1,0,0,0,1,0,0],"id":7,"left_children":[1,3,5,-1,-1,-1,7,-1,-1],"loss_changes":[2.3364067E2,5.748291E-1,1.2342499E1,0E0,0E0,0E0,1.2036133E-1,0E0,0E0],"parents":[2147483647,0,0,1,1,2,2,6,6],"right_children":[2,4,6,-1,-1,-1,8,-1,-1],"split_conditions":[-1.7700603E0,-2.75795E0,-5.030259E-1,7.558027E-2,4.9596634E-2,-1.3020376E-2,1.3042789E0,-7.273255E-2,-5.0595857E-2],"split_indices":[14,12,12,0,0,0,4,0,0],"split_type":[0,0,0,0,0,0,0,0,0],"sum_hessian":[1.3432155E2,5.5794147E1,7.8527405E1,4.472827E1,1.1065874E1,1.1827128E1,6.670027E1,5.4974697E1,1.1725577E1],"tree_param":{"num_deleted":"0","num_feature":"30","num_nodes":"9","size_leaf_vector":"0"}},{"base_weights":[-1.7773786E-1,-1.4999225E0,1.5014843E0],"categories":[],"categories_nodes":[],"categories_segments":[],"categories_sizes":[],"default_left":[1,0,0],"id":8,"left_children":[1,-1,-1],"loss_changes":[2.9430026E2,0E0,0E0],"parents":[2147483647,0,0],"right_children":[2,-1,-1],"split_conditions":[-9.904957E-1,-7.499613E-2,7.507422E-2],"split_indices":[0,0,0],"split_type":[0,0,0],"sum_hessian":[1.3053891E2,7.309343E1,5.7445477E1],"tree_param":{"num_deleted":"0","num_feature":"30","num_nodes":"3","size_leaf_vector":"0"}},{"base_weights":[-1.424209E-1,-1.4632964E0,1.4612696E0],"categories":[],"categories_nodes":[],"categories_segments":[],"categories_sizes":[],"default_left":[1,0,0],"id":9,"left_children":[1,-1,-1],"loss_changes":[2.762591E2,0E0,0E0],"parents":[2147483647,0,0],"right_children":[2,-1,-1],"split_conditions":[-9.9010205E-1,-7.316482E-2,7.3063485E-2],"split_indices":[0,0,0],"split_type":[0,0,0],"sum_hessian":[1.2840756E2,7.0460495E1,5.794706E1],"tree_param":{"num_deleted":"0","num_feature":"30","num_nodes":"3","size_leaf_vector":"0"}},{"base_weights":[-9.492904E-2,-1.4285034E0,1.4303802E0],"categories":[],"categories_nodes":[],"categories_segments":[],"categories_sizes":[],"default_left":[1,0,0],"id":10,"left_children":[1,-1,-1],"loss_changes":[2.6543137E2,0E0,0E0],"parents":[2147483647,0,0],"right_children":[2,-1,-1],"split_conditions":[-9.904898E-1,-7.142517E-2,7.151901E-2],"split_indices":[0,0,0],"split_type":[0,0,0],"sum_hessian":[1.2848544E2,6.858511E1,5.9900337E1],"tree_param":{"num_deleted":"0","num_feature":"30","num_nodes":"3","size_leaf_vector":"0"}},{"base_weights":[-9.5128536E-2,-1.3953608E0,1.3993106E0],"categories":[],"categories_nodes":[],"categories_segments":[],"categories_sizes":[],"default_left":[1,0,0],"id":11,"left_children":[1,-1,-1],"loss_changes":[2.3455038E2,0E0,0E0],"parents":[2147483647,0,0],"right_children":[2,-1,-1],"split_conditions":[-9.904898E-1,-6.976804E-2,6.9965534E-2],"split_indices":[0,0,0],"split_type":[0,0,0],"sum_hessian":[1.1870339E2,6.351161E1,5.5191788E1],"tree_param":{"num_deleted":"0","num_feature":"30","num_nodes":"3","size_leaf_vector":"0"}},{"base_weights":[-1.03423856E-1,-1.368878E0,1.3698846E0],"categories":[],"categories_nodes":[],"categories_segments":[],"categories_sizes":[],"default_left":[1,0,0],"id":12,"left_children":[1,-1,-1],"loss_changes":[2.2653683E2,0E0,0E0],"parents":[2147483647,0,0],"right_children":[2,-1,-1],"split_conditions":[-9.9010205E-1,-6.84439E-2,6.849423E-2],"split_indices":[0,0,0],"split_type":[0,0,0],"sum_hessian":[1.1950049E2,6.432303E1,5.5177456E1],"tree_param":{"num_deleted":"0","num_feature":"30","num_nodes":"3","size_leaf_vector":"0"}},{"base_weights":[-1.133679E-1,-1.3431584E0,1.3429528E0],"categories":[],"categories_nodes":[],"categories_segments":[],"categories_sizes":[],"default_left":[1,0,0],"id":13,"left_children":[1,-1,-1],"loss_changes":[2.0825146E2,0E0,0E0],"parents":[2147483647,0,0],"right_children":[2,-1,-1],"split_conditions":[-9.904898E-1,-6.715792E-2,6.714764E-2],"split_indices":[0,0,0],"split_type":[0,0,0],"sum_hessian":[1.1427147E2,6.1996346E1,5.2275127E1],"tree_param":{"num_deleted":"0","num_feature":"30","num_nodes":"3","size_leaf_vector":"0"}},{"base_weights":[-7.535419E-2,-1.3166757E0,1.3213884E0],"categories":[],"categories_nodes":[],"categories_segments":[],"categories_sizes":[],"default_left":[1,0,0],"id":14,"left_children":[1,-1,-1],"loss_changes":[1.9275053E2,0E0,0E0],"parents":[2147483647,0,0],"right_children":[2,-1,-1],"split_conditions":[-9.904957E-1,-6.5833785E-2,6.606942E-2],"split_indices":[0,0,0],"split_type":[0,0,0],"sum_hessian":[1.091684E2,5.783037E1,5.133803E1],"tree_param":{"num_deleted":"0","num_feature":"30","num_nodes":"3","size_leaf_vector":"0"}},{"base_weights":[-1.2757935E-1,-1.2968197E0,1.294961E0],"categories":[],"categories_nodes":[],"categories_segments":[],"categories_sizes":[],"default_left":[1,0,0],"id":15,"left_children":[1,-1,-1],"loss_changes":[1.8073808E2,0E0,0E0],"parents":[2147483647,0,0],"right_children":[2,-1,-1],"split_conditions":[-9.666643E-1,-6.484099E-2,6.474805E-2],"split_indices":[0,0,0],"split_type":[0,0,0],"sum_hessian":[1.0665325E2,5.8586853E1,4.8066402E1],"tree_param":{"num_deleted":"0","num_feature":"30","num_nodes":"3","size_leaf_vector":"0"}},{"base_weights":[-1.1298868E-1,1.2219584E0,-9.314648E-1,-1.1010702E0,-1.8034358E-1,-7.414725E-1,-1.1843319E0],"categories":[],"categories_nodes":[],"categories_segments":[],"categories_sizes":[],"default_left":[1,0,1,1,0,0,0],"id":16,"left_children":[1,-1,3,5,-1,-1,-1],"loss_changes":[1.1339853E2,0E0,7.9878235E0,6.8556976E-1,0E0,0E0,0E0],"parents":[2147483647,0,0,2,2,3,3],"right_children":[2,-1,4,6,-1,-1,-1],"split_conditions":[-1.4541839E0,6.109792E-2,5.3652817E-1,-2.358015E-1,-9.01718E-3,-3.7073623E-2,-5.9216596E-2],"split_indices":[12,0,17,12,0,0,0],"split_type":[0,0,0,0,0,0,0],"sum_hessian":[1.0174394E2,3.8483612E1,6.326033E1,5.122718E1,1.203315E1,1.1493489E1,3.9733692E1],"tree_param":{"num_deleted":"0","num_feature":"30","num_nodes":"7","size_leaf_vector":"0"}},{"base_weights":[-7.859715E-2,-1.2622397E0,1.2636325E0],"categories":[],"categories_nodes":[],"categories_segments":[],"categories_sizes":[],"default_left":[1,0,0],"id":17,"left_children":[1,-1,-1],"loss_changes":[1.6595007E2,0E0,0E0],"parents":[2147483647,0,0],"right_children":[2,-1,-1],"split_conditions":[-9.904898E-1,-6.311198E-2,6.318163E-2],"split_indices":[0,0,0],"split_type":[0,0,0],"sum_hessian":[1.0245124E2,5.447349E1,4.7977745E1],"tree_param":{"num_deleted":"0","num_feature":"30","num_nodes":"3","size_leaf_vector":"0"}},{"base_weights":[-9.1198705E-2,-1.244682E0,1.246909E0],"categories":[],"categories_nodes":[],"categories_segments":[],"categories_sizes":[],"default_left":[1,0,0],"id":18,"left_children":[1,-1,-1],"loss_changes":[1.5364034E2,0E0,0E0],"parents":[2147483647,0,0],"right_children":[2,-1,-1],"split_conditions":[-9.904898E-1,-6.22341E-2,6.2345453E-2],"split_indices":[0,0,0],"split_type":[0,0,0],"sum_hessian":[9.753567E1,5.241898E1,4.511669E1],"tree_param":{"num_deleted":"0","num_feature":"30","num_nodes":"3","size_leaf_vector":"0"}},{"base_weights":[-1.18610464E-1,1.0584567E0,-1.0044562E0,1.2021797E0,6.086618E-1,-1.1440716E0,-4.1258198E-1],"categories":[],"categories_nodes":[],"categories_segments":[],"categories_sizes":[],"default_left":[1,1,1,0,0,0,0],"id":19,"left_children":[1,3,5,-1,-1,-1,-1],"loss_changes":[1.0108857E2,1.9627419E0,4.0934525E0,0E0,0E0,0E0,0E0],"parents":[2147483647,0,0,1,1,2,2],"right_children":[2,4,6,-1,-1,-1,-1],"split_conditions":[-5.287653E-1,-2.7640345E0,1.3461548E0,6.0108986E-2,3.0433089E-2,-5.720358E-2,-2.0629099E-2],"split_indices":[3,10,4,0,0,0,0],"split_type":[0,0,0,0,0,0,0],"sum_hessian":[9.492922E1,4.068036E1,5.4248867E1,2.9561762E1,1.1118597E1,4.3139786E1,1.1109078E1],"tree_param":{"num_deleted":"0","num_feature":"30","num_nodes":"7","size_leaf_vector":"0"}},{"base_weights":[-8.721072E-2,1.0200078E0,-9.8232806E-1,1.190144E0,4.9521887E-1,-1.0970327E0,-5.132396E-1],"categories":[],"categories_nodes":[],"categories_segments":[],"categories_sizes":[],"default_left":[1,1,1,0,0,0,0],"id":20,"left_children":[1,3,5,-1,-1,-1,-1],"loss_changes":[9.3624954E1,3.1846008E0,2.2449608E0,0E0,0E0,0E0,0E0],"parents":[2147483647,0,0,1,1,2,2],"right_children":[2,4,6,-1,-1,-1,-1],"split_conditions":[-3.3406308E-1,-2.8770914E0,1.3489428E0,5.95072E-2,2.4760945E-2,-5.4851633E-2,-2.566198E-2],"split_indices":[3,12,4,0,0,0,0],"split_type":[0,0,0,0,0,0,0],"sum_hessian":[9.245562E1,4.126867E1,5.118695E1,3.0207552E1,1.1061118E1,4.005403E1,1.1132919E1],"tree_param":{"num_deleted":"0","num_feature":"30","num_nodes":"7","size_leaf_vector":"0"}},{"base_weights":[-9.159231E-2,-1.2050987E0,1.2121878E0],"categories":[],"categories_nodes":[],"categories_segments":[],"categories_sizes":[],"default_left":[1,0,0],"id":21,"left_children":[1,-1,-1],"loss_changes":[1.3509196E2,0E0,0E0],"parents":[2147483647,0,0],"right_children":[2,-1,-1],"split_conditions":[-9.904898E-1,-6.025494E-2,6.060939E-2],"split_indices":[0,0,0],"split_type":[0,0,0],"sum_hessian":[9.104722E1,4.9147766E1,4.1899452E1],"tree_param":{"num_deleted":"0","num_feature":"30","num_nodes":"3","size_leaf_vector":"0"}},{"base_weights":[-7.04211E-2,-1.1916821E0,1.1955882E0],"categories":[],"categories_nodes":[],"categories_segments":[],"categories_sizes":[],"default_left":[1,0,0],"id":22,"left_children":[1,-1,-1],"loss_changes":[1.2438474E2,0E0,0E0],"parents":[2147483647,0,0],"right_children":[2,-1,-1],"split_conditions":[-9.904957E-1,-5.9584107E-2,5.9779413E-2],"split_indices":[0,0,0],"split_type":[0,0,0],"sum_hessian":[8.56204E1,4.543706E1,4.018334E1],"tree_param":{"num_deleted":"0","num_feature":"30","num_nodes":"3","size_leaf_vector":"0"}},{"base_weights":[-8.1082694E-2,1.0142868E0,-8.981494E-1,1.1462575E0,6.4530593E-1,-4.610627E-1,-1.0193034E0],"categories":[],"categories_nodes":[],"categories_segments":[],"categories_sizes":[],"default_left":[1,1,1,0,0,0,0],"id":23,"left_children":[1,3,5,-1,-1,-1,-1],"loss_changes":[7.81216E1,1.077961E0,2.1747284E0,0E0,0E0,0E0,0E0],"parents":[2147483647,0,0,1,1,2,2],"right_children":[2,4,6,-1,-1,-1,-1],"split_conditions":[-1.6166106E0,-4.875525E0,2.0962292E-1,5.7312876E-2,3.2265298E-2,-2.3053136E-2,-5.096517E-2],"split_indices":[14,14,3,0,0,0,0],"split_type":[0,0,0,0,0,0,0],"sum_hessian":[8.526982E1,3.6327442E1,4.8942383E1,2.5205732E1,1.1121711E1,1.1664832E1,3.727755E1],"tree_param":{"num_deleted":"0","num_feature":"30","num_nodes":"7","size_leaf_vector":"0"}},{"base_weights":[-8.573022E-2,-1.1702914E0,1.1735806E0],"categories":[],"categories_nodes":[],"categories_segments":[],"categories_sizes":[],"default_left":[1,0,0],"id":24,"left_children":[1,-1,-1],"loss_changes":[1.1203834E2,0E0,0E0],"parents":[2147483647,0,0],"right_children":[2,-1,-1],"split_conditions":[-9.904898E-1,-5.8514573E-2,5.8679033E-2],"split_indices":[0,0,0],"split_type":[0,0,0],"sum_hessian":[8.002573E1,4.303404E1,3.6991684E1],"tree_param":{"num_deleted":"0","num_feature":"30","num_nodes":"3","size_leaf_vector":"0"}},{"base_weights":[-9.9261254E-2,-1.1588389E0,1.1632543E0],"categories":[],"categories_nodes":[],"categories_segments":[],"categories_sizes":[],"default_left":[1,0,0],"id":25,"left_children":[1,-1,-1],"loss_changes":[1.08654526E2,0E0,0E0],"parents":[2147483647,0,0],"right_children":[2,-1,-1],"split_conditions":[-9.904898E-1,-5.7941943E-2,5.8162715E-2],"split_indices":[0,0,0],"split_type":[0,0,0],"sum_hessian":[7.921517E1,4.3113712E1,3.610146E1],"tree_param":{"num_deleted":"0","num_feature":"30","num_nodes":"3","size_leaf_vector":"0"}},{"base_weights":[-1.1957253E-1,-1.1458551E0,1.1479847E0],"categories":[],"categories_nodes":[],"categories_segments":[],"categories_sizes":[],"default_left":[1,0,0],"id":26,"left_children":[1,-1,-1],"loss_changes":[9.7379074E1,0E0,0E0],"parents":[2147483647,0,0],"right_children":[2,-1,-1],"split_conditions":[-9.904898E-1,-5.7292756E-2,5.739924E-2],"split_indices":[0,0,0],"split_type":[0,0,0],"sum_hessian":[7.28456E1,4.0306942E1,3.2538654E1],"tree_param":{"num_deleted":"0","num_feature":"30","num_nodes":"3","size_leaf_vector":"0"}},{"base_weights":[-7.8049436E-2,1.0890572E0,-7.7320206E-1,-9.496001E-1,-2.1217668E-1],"categories":[],"categories_nodes":[],"categories_segments":[],"categories_sizes":[],"default_left":[1,0,1,0,0],"id":27,"left_children":[1,-1,3,-1,-1],"loss_changes":[5.8062485E1,0E0,4.2306767E0,0E0,0E0],"parents":[2147483647,0,0,2,2],"right_children":[2,-1,4,-1,-1],"split_conditions":[-1.5082998E0,5.4452863E-2,1.2917612E0,-4.7480006E-2,-1.0608834E-2],"split_indices":[10,0,4,0,0],"split_type":[0,0,0,0,0],"sum_hessian":[6.95278E1,2.5742134E1,4.3785667E1,3.278482E1,1.1000845E1],"tree_param":{"num_deleted":"0","num_feature":"30","num_nodes":"5","size_leaf_vector":"0"}},{"base_weights":[-3.503098E-2,-1.1269847E0,1.1347237E0],"categories":[],"categories_nodes":[],"categories_segments":[],"categories_sizes":[],"default_left":[1,0,0],"id":28,"left_children":[1,-1,-1],"loss_changes":[8.750914E1,0E0,0E0],"parents":[2147483647,0,0],"right_children":[2,-1,-1],"split_conditions":[-9.904898E-1,-5.6349237E-2,5.6736182E-2],"split_indices":[0,0,0],"split_type":[0,0,0],"sum_hessian":[6.6508896E1,3.4417286E1,3.209161E1],"tree_param":{"num_deleted":"0","num_feature":"30","num_nodes":"3","size_leaf_vector":"0"}},{"base_weights":[-9.3017064E-2,1.040403E0,-7.5233185E-1,-9.3617034E-1,-2.0432489E-1],"categories":[],"categories_nodes":[],"categories_segments":[],"categories_sizes":[],"default_left":[1,0,1,0,0],"id":29,"left_children":[1,-1,3,-1,-1],"loss_changes":[5.0949963E1,0E0,4.1431446E0,0E0,0E0],"parents":[2147483647,0,0,2,2],"right_children":[2,-1,4,-1,-1],"split_conditions":[-1.452816E0,5.202015E-2,4.0783465E-1,-4.680852E-2,-1.02162445E-2],"split_indices":[12,0,17,0,0],"split_type":[0,0,0,0,0],"sum_hessian":[6.6133064E1,2.4109211E1,4.2023853E1,3.0937138E1,1.1086717E1],"tree_param":{"num_deleted":"0","num_feature":"30","num_nodes":"5","size_leaf_vector":"0"}},{"base_weights":[-4.2135596E-2,-1.1111646E0,1.1182286E0],"categories":[],"categories_nodes":[],"categories_segments":[],"categories_sizes":[],"default_left":[1,0,0],"id":30,"left_children":[1,-1,-1],"loss_changes":[7.9175995E1,0E0,0E0],"parents":[2147483647,0,0],"right_children":[2,-1,-1],"split_conditions":[-9.904898E-1,-5.555823E-2,5.591143E-2],"split_indices":[0,0,0],"split_type":[0,0,0],"sum_hessian":[6.182611E1,3.220159E1,2.9624521E1],"tree_param":{"num_deleted":"0","num_feature":"30","num_nodes":"3","size_leaf_vector":"0"}},{"base_weights":[-5.7558216E-2,-1.1017592E0,1.1093098E0],"categories":[],"categories_nodes":[],"categories_segments":[],"categories_sizes":[],"default_left":[1,0,0],"id":31,"left_children":[1,-1,-1],"loss_changes":[7.750242E1,0E0,0E0],"parents":[2147483647,0,0],"right_children":[2,-1,-1],"split_conditions":[-9.904898E-1,-5.508796E-2,5.546549E-2],"split_indices":[0,0,0],"split_type":[0,0,0],"sum_hessian":[6.160458E1,3.2540604E1,2.9063974E1],"tree_param":{"num_deleted":"0","num_feature":"30","num_nodes":"3","size_leaf_vector":"0"}},{"base_weights":[-7.77912E-2,-1.0958642E0,1.1022787E0],"categories":[],"categories_nodes":[],"categories_segments":[],"categories_sizes":[],"default_left":[1,0,0],"id":32,"left_children":[1,-1,-1],"loss_changes":[7.254346E1,0E0,0E0],"parents":[2147483647,0,0],"right_children":[2,-1,-1],"split_conditions":[-9.904898E-1,-5.479321E-2,5.5113938E-2],"split_indices":[0,0,0],"split_type":[0,0,0],"sum_hessian":[5.837712E1,3.1377983E1,2.6999136E1],"tree_param":{"num_deleted":"0","num_feature":"30","num_nodes":"3","size_leaf_vector":"0"}},{"base_weights":[-7.88496E-2,-1.0858971E0,1.0902257E0],"categories":[],"categories_nodes":[],"categories_segments":[],"categories_sizes":[],"default_left":[1,0,0],"id":33,"left_children":[1,-1,-1],"loss_changes":[6.611405E1,0E0,0E0],"parents":[2147483647,0,0],"right_children":[2,-1,-1],"split_conditions":[-9.904898E-1,-5.4294854E-2,5.4511286E-2],"split_indices":[0,0,0],"split_type":[0,0,0],"sum_hessian":[5.41511E1,2.9129742E1,2.502136E1],"tree_param":{"num_deleted":"0","num_feature":"30","num_nodes":"3","size_leaf_vector":"0"}},{"base_weights":[-5.1915355E-2,-1.0786331E0,1.08612E0],"categories":[],"categories_nodes":[],"categories_segments":[],"categories_sizes":[],"default_left":[1,0,0],"id":34,"left_children":[1,-1,-1],"loss_changes":[6.604614E1,0E0,0E0],"parents":[2147483647,0,0],"right_children":[2,-1,-1],"split_conditions":[-9.904898E-1,-5.3931653E-2,5.4306E-2],"split_indices":[0,0,0],"split_type":[0,0,0],"sum_hessian":[5.452237E1,2.869047E1,2.58319E1],"tree_param":{"num_deleted":"0","num_feature":"30","num_nodes":"3","size_leaf_vector":"0"}},{"base_weights":[-8.969977E-2,9.0922993E-1,-7.8611916E-1,-4.7232956E-1,-9.431111E-1],"categories":[],"categories_nodes":[],"categories_segments":[],"categories_sizes":[],"default_left":[1,0,1,0,0],"id":35,"left_children":[1,-1,3,-1,-1],"loss_changes":[3.6957764E1,0E0,1.0931644E0,0E0,0E0],"parents":[2147483647,0,0,2,2],"right_children":[2,-1,4,-1,-1],"split_conditions":[-1.6166106E0,4.54615E-2,-4.8694942E-2,-2.3616478E-2,-4.7155555E-2],"split_indices":[14,0,12,0,0],"split_type":[0,0,0,0,0],"sum_hessian":[5.1097687E1,2.0864498E1,3.0233189E1,1.1418649E1,1.8814539E1],"tree_param":{"num_deleted":"0","num_feature":"30","num_nodes":"5","size_leaf_vector":"0"}},{"base_weights":[-4.6472028E-2,1.0236313E0,-6.813901E-1,-8.805713E-1,-2.6403597E-1],"categories":[],"categories_nodes":[],"categories_segments":[],"categories_sizes":[],"default_left":[1,0,1,0,0],"id":36,"left_children":[1,-1,3,-1,-1],"loss_changes":[3.594246E1,0E0,2.5238733E0,0E0,0E0],"parents":[2147483647,0,0,2,2],"right_children":[2,-1,4,-1,-1],"split_conditions":[-1.8383533E0,5.1181566E-2,1.9461541E-1,-4.4028565E-2,-1.3201798E-2],"split_indices":[12,0,18,0,0],"split_type":[0,0,0,0,0],"sum_hessian":[5.0874474E1,1.871672E1,3.2157753E1,2.1017374E1,1.1140378E1],"tree_param":{"num_deleted":"0","num_feature":"30","num_nodes":"5","size_leaf_vector":"0"}},{"base_weights":[-8.386409E-2,-1.0645553E0,1.0671587E0],"categories":[],"categories_nodes":[],"categories_segments":[],"categories_sizes":[],"default_left":[1,0,0],"id":37,"left_children":[1,-1,-1],"loss_changes":[5.756698E1,0E0,0E0],"parents":[2147483647,0,0],"right_children":[2,-1,-1],"split_conditions":[-9.904898E-1,-5.3227764E-2,5.3357936E-2],"split_indices":[0,0,0],"split_type":[0,0,0],"sum_hessian":[4.8992054E1,2.649391E1,2.2498144E1],"tree_param":{"num_deleted":"0","num_feature":"30","num_nodes":"3","size_leaf_vector":"0"}},{"base_weights":[-9.288836E-2,-1.0591087E0,1.0621909E0],"categories":[],"categories_nodes":[],"categories_segments":[],"categories_sizes":[],"default_left":[1,0,0],"id":38,"left_children":[1,-1,-1],"loss_changes":[5.6303352E1,0E0,0E0],"parents":[2147483647,0,0],"right_children":[2,-1,-1],"split_conditions":[-9.9010795E-1,-5.2955437E-2,5.3109545E-2],"split_indices":[0,0,0],"split_type":[0,0,0],"sum_hessian":[4.844028E1,2.6421696E1,2.2018587E1],"tree_param":{"num_deleted":"0","num_feature":"30","num_nodes":"3","size_leaf_vector":"0"}},{"base_weights":[-7.125355E-2,-1.0500405E0,1.0557383E0],"categories":[],"categories_nodes":[],"categories_segments":[],"categories_sizes":[],"default_left":[1,0,0],"id":39,"left_children":[1,-1,-1],"loss_changes":[5.1464012E1,0E0,0E0],"parents":[2147483647,0,0],"right_children":[2,-1,-1],"split_conditions":[-9.904898E-1,-5.2502025E-2,5.2786916E-2],"split_indices":[0,0,0],"split_type":[0,0,0],"sum_hessian":[4.464965E1,2.3932592E1,2.071706E1],"tree_param":{"num_deleted":"0","num_feature":"30","num_nodes":"3","size_leaf_vector":"0"}},{"base_weights":[-7.32057E-2,-1.0437487E0,1.0472556E0],"categories":[],"categories_nodes":[],"categories_segments":[],"categories_sizes":[],"default_left":[1,0,0],"id":40,"left_children":[1,-1,-1],"loss_changes":[4.9003235E1,0E0,0E0],"parents":[2147483647,0,0],"right_children":[2,-1,-1],"split_conditions":[-9.904898E-1,-5.218744E-2,5.236278E-2],"split_indices":[0,0,0],"split_type":[0,0,0],"sum_hessian":[4.3057102E1,2.3108767E1,1.9948336E1],"tree_param":{"num_deleted":"0","num_feature":"30","num_nodes":"3","size_leaf_vector":"0"}},{"base_weights":[-8.188875E-2,-1.035928E0,1.0371381E0],"categories":[],"categories_nodes":[],"categories_segments":[],"categories_sizes":[],"default_left":[1,0,0],"id":41,"left_children":[1,-1,-1],"loss_changes":[4.541936E1,0E0,0E0],"parents":[2147483647,0,0],"right_children":[2,-1,-1],"split_conditions":[-9.9010205E-1,-5.1796403E-2,5.1856905E-2],"split_indices":[0,0,0],"split_type":[0,0,0],"sum_hessian":[4.0537228E1,2.1921803E1,1.8615425E1],"tree_param":{"num_deleted":"0","num_feature":"30","num_nodes":"3","size_leaf_vector":"0"}},{"base_weights":[-5.8369737E-2,-1.0311725E0,1.036726E0],"categories":[],"categories_nodes":[],"categories_segments":[],"categories_sizes":[],"default_left":[1,0,0],"id":42,"left_children":[1,-1,-1],"loss_changes":[4.435759E1,0E0,0E0],"parents":[2147483647,0,0],"right_children":[2,-1,-1],"split_conditions":[-9.904957E-1,-5.1558625E-2,5.18363E-2],"split_indices":[0,0,0],"split_type":[0,0,0],"sum_hessian":[3.9634613E1,2.102019E1,1.8614422E1],"tree_param":{"num_deleted":"0","num_feature":"30","num_nodes":"3","size_leaf_vector":"0"}},{"base_weights":[-6.3382566E-2,-1.0264597E0,1.0292301E0],"categories":[],"categories_nodes":[],"categories_segments":[],"categories_sizes":[],"default_left":[1,0,0],"id":43,"left_children":[1,-1,-1],"loss_changes":[4.2439663E1,0E0,0E0],"parents":[2147483647,0,0],"right_children":[2,-1,-1],"split_conditions":[-9.904957E-1,-5.1322985E-2,5.1461507E-2],"split_indices":[0,0,0],"split_type":[0,0,0],"sum_hessian":[3.8327545E1,2.0403522E1,1.792402E1],"tree_param":{"num_deleted":"0","num_feature":"30","num_nodes":"3","size_leaf_vector":"0"}},{"base_weights":[-1.060439E-1,9.244013E-1,-6.6765547E-1,-3.878883E-1,-8.597697E-1],"categories":[],"categories_nodes":[],"categories_segments":[],"categories_sizes":[],"default_left":[1,0,1,0,0],"id":44,"left_children":[1,-1,3,-1,-1],"loss_changes":[2.2516167E1,0E0,1.0141068E0,0E0,0E0],"parents":[2147483647,0,0,2,2],"right_children":[2,-1,4,-1,-1],"split_conditions":[-1.5113981E0,4.6220064E-2,4.3599308E-2,-1.9394416E-2,-4.2988487E-2],"split_indices":[10,0,12,0,0],"split_type":[0,0,0,0,0],"sum_hessian":[3.6841038E1,1.2768115E1,2.4072924E1,1.1029793E1,1.3043131E1],"tree_param":{"num_deleted":"0","num_feature":"30","num_nodes":"5","size_leaf_vector":"0"}},{"base_weights":[-3.466138E-2,-1.0151953E0,1.0221479E0],"categories":[],"categories_nodes":[],"categories_segments":[],"categories_sizes":[],"default_left":[1,0,0],"id":45,"left_children":[1,-1,-1],"loss_changes":[3.84117E1,0E0,0E0],"parents":[2147483647,0,0],"right_children":[2,-1,-1],"split_conditions":[-9.904898E-1,-5.0759763E-2,5.1107395E-2],"split_indices":[0,0,0],"split_type":[0,0,0],"sum_hessian":[3.5067047E1,1.821038E1,1.6856667E1],"tree_param":{"num_deleted":"0","num_feature":"30","num_nodes":"3","size_leaf_vector":"0"}},{"base_weights":[-6.003066E-2,-1.0114572E0,1.0138252E0],"categories":[],"categories_nodes":[],"categories_segments":[],"categories_sizes":[],"default_left":[1,0,0],"id":46,"left_children":[1,-1,-1],"loss_changes":[3.6926205E1,0E0,0E0],"parents":[2147483647,0,0],"right_children":[2,-1,-1],"split_conditions":[-9.904898E-1,-5.057286E-2,5.069126E-2],"split_indices":[0,0,0],"split_type":[0,0,0],"sum_hessian":[3.413844E1,1.8131874E1,1.6006567E1],"tree_param":{"num_deleted":"0","num_feature":"30","num_nodes":"3","size_leaf_vector":"0"}},{"base_weights":[-5.8833897E-2,-1.0036134E0,1.0064877E0],"categories":[],"categories_nodes":[],"categories_segments":[],"categories_sizes":[],"default_left":[1,0,0],"id":47,"left_children":[1,-1,-1],"loss_changes":[3.3859417E1,0E0,0E0],"parents":[2147483647,0,0],"right_children":[2,-1,-1],"split_conditions":[-9.904898E-1,-5.018067E-2,5.0324388E-2],"split_indices":[0,0,0],"split_type":[0,0,0],"sum_hessian":[3.1637346E1,1.679799E1,1.4839356E1],"tree_param":{"num_deleted":"0","num_feature":"30","num_nodes":"3","size_leaf_vector":"0"}},{"base_weights":[-3.7766848E-2,-9.99751E-1,1.0055386E0],"categories":[],"categories_nodes":[],"categories_segments":[],"categories_sizes":[],"default_left":[1,0,0],"id":48,"left_children":[1,-1,-1],"loss_changes":[3.363435E1,0E0,0E0],"parents":[2147483647,0,0],"right_children":[2,-1,-1],"split_conditions":[-9.904898E-1,-4.998755E-2,5.027693E-2],"split_indices":[0,0,0],"split_type":[0,0,0],"sum_hessian":[3.1510618E1,1.641596E1,1.5094659E1],"tree_param":{"num_deleted":"0","num_feature":"30","num_nodes":"3","size_leaf_vector":"0"}},{"base_weights":[-7.457389E-2,-9.9580985E-1,9.941769E-1],"categories":[],"categories_nodes":[],"categories_segments":[],"categories_sizes":[],"default_left":[1,0,0],"id":49,"left_children":[1,-1,-1],"loss_changes":[3.118572E1,0E0,0E0],"parents":[2147483647,0,0],"right_children":[2,-1,-1],"split_conditions":[-9.904898E-1,-4.9790494E-2,4.9708847E-2],"split_indices":[0,0,0],"split_type":[0,0,0],"sum_hessian":[2.9668879E1,1.5970749E1,1.369813E1],"tree_param":{"num_deleted":"0","num_feature":"30","num_nodes":"3","size_leaf_vector":"0"}},{"base_weights":[-7.868895E-2,-9.914889E-1,9.8961455E-1],"categories":[],"categories_nodes":[],"categories_segments":[],"categories_sizes":[],"default_left":[1,0,0],"id":50,"left_children":[1,-1,-1],"loss_changes":[3.036173E1,0E0,0E0],"parents":[2147483647,0,0],"right_children":[2,-1,-1],"split_conditions":[-9.9010205E-1,-4.9574446E-2,4.948073E-2],"split_indices":[0,0,0],"split_type":[0,0,0],"sum_hessian":[2.9129333E1,1.5746672E1,1.3382663E1],"tree_param":{"num_deleted":"0","num_feature":"30","num_nodes":"3","size_leaf_vector":"0"}},{"base_weights":[-5.912191E-2,-9.8349154E-1,9.841893E-1],"categories":[],"categories_nodes":[],"categories_segments":[],"categories_sizes":[],"default_left":[1,0,0],"id":51,"left_children":[1,-1,-1],"loss_changes":[2.8170774E1,0E0,0E0],"parents":[2147483647,0,0],"right_children":[2,-1,-1],"split_conditions":[-9.904898E-1,-4.9174577E-2,4.9209464E-2],"split_indices":[0,0,0],"split_type":[0,0,0],"sum_hessian":[2.7206852E1,1.4456121E1,1.27507305E1],"tree_param":{"num_deleted":"0","num_feature":"30","num_nodes":"3","size_leaf_vector":"0"}},{"base_weights":[-5.624151E-2,7.572392E-1,-7.3798054E-1],"categories":[],"categories_nodes":[],"categories_segments":[],"categories_sizes":[],"default_left":[1,0,0],"id":52,"left_children":[1,-1,-1],"loss_changes":[1.5249938E1,0E0,0E0],"parents":[2147483647,0,0],"right_children":[2,-1,-1],"split_conditions":[-2.732252E-1,3.7861962E-2,-3.6899026E-2],"split_indices":[3,0,0],"split_type":[0,0,0],"sum_hessian":[2.549044E1,1.1571763E1,1.3918678E1],"tree_param":{"num_deleted":"0","num_feature":"30","num_nodes":"3","size_leaf_vector":"0"}},{"base_weights":[-6.897885E-2,-9.753288E-1,9.746156E-1],"categories":[],"categories_nodes":[],"categories_segments":[],"categories_sizes":[],"default_left":[1,0,0],"id":53,"left_children":[1,-1,-1],"loss_changes":[2.553362E1,0E0,0E0],"parents":[2147483647,0,0],"right_children":[2,-1,-1],"split_conditions":[-9.904898E-1,-4.876644E-2,4.873078E-2],"split_indices":[0,0,0],"split_type":[0,0,0],"sum_hessian":[2.4990108E1,1.34095125E1,1.1580596E1],"tree_param":{"num_deleted":"0","num_feature":"30","num_nodes":"3","size_leaf_vector":"0"}},{"base_weights":[-8.674403E-2,-9.7305423E-1,9.6940935E-1],"categories":[],"categories_nodes":[],"categories_segments":[],"categories_sizes":[],"default_left":[1,0,0],"id":54,"left_children":[1,-1,-1],"loss_changes":[2.4753305E1,0E0,0E0],"parents":[2147483647,0,0],"right_children":[2,-1,-1],"split_conditions":[-9.904898E-1,-4.8652712E-2,4.8470467E-2],"split_indices":[0,0,0],"split_type":[0,0,0],"sum_hessian":[2.4435892E1,1.3329027E1,1.1106866E1],"tree_param":{"num_deleted":"0","num_feature":"30","num_nodes":"3","size_leaf_vector":"0"}},{"base_weights":[-7.97319E-2,-9.597553E-1,8.47086E-1],"categories":[],"categories_nodes":[],"categories_segments":[],"categories_sizes":[],"default_left":[1,0,0],"id":55,"left_children":[1,-1,-1],"loss_changes":[2.0072435E1,0E0,0E0],"parents":[2147483647,0,0],"right_children":[2,-1,-1],"split_conditions":[-9.909303E-1,-4.7987767E-2,4.23543E-2],"split_indices":[0,0,0],"split_type":[0,0,0],"sum_hessian":[2.261321E1,1.15812E1,1.103201E1],"tree_param":{"num_deleted":"0","num_feature":"30","num_nodes":"3","size_leaf_vector":"0"}},{"base_weights":[-5.334361E-2],"categories":[],"categories_nodes":[],"categories_segments":[],"categories_sizes":[],"default_left":[0],"id":56,"left_children":[-1],"loss_changes":[0E0],"parents":[2147483647],"right_children":[-1],"split_conditions":[-2.6671805E-3],"split_indices":[0],"split_type":[0],"sum_hessian":[2.1994917E1],"tree_param":{"num_deleted":"0","num_feature":"30","num_nodes":"1","size_leaf_vector":"0"}},{"base_weights":[-3.4992874E-2,6.11014E-1,-6.7107624E-1],"categories":[],"categories_nodes":[],"categories_segments":[],"categories_sizes":[],"default_left":[1,0,0],"id":57,"left_children":[1,-1,-1],"loss_changes":[9.92969E0,0E0,0E0],"parents":[2147483647,0,0],"right_children":[2,-1,-1],"split_conditions":[-6.0626704E-1,3.0550702E-2,-3.3553813E-2],"split_indices":[14,0,0],"split_type":[0,0,0],"sum_hessian":[2.2167007E1,1.101727E1,1.1149737E1],"tree_param":{"num_deleted":"0","num_feature":"30","num_nodes":"3","size_leaf_vector":"0"}},{"base_weights":[-6.3787445E-2,-9.5462E-1,8.3671254E-1],"categories":[],"categories_nodes":[],"categories_segments":[],"categories_sizes":[],"default_left":[1,0,0],"id":58,"left_children":[1,-1,-1],"loss_changes":[1.931944E1,0E0,0E0],"parents":[2147483647,0,0],"right_children":[2,-1,-1],"split_conditions":[-9.909362E-1,-4.7731E-2,4.183563E-2],"split_indices":[0,0,0],"split_type":[0,0,0],"sum_hessian":[2.2087536E1,1.1073156E1,1.1014379E1],"tree_param":{"num_deleted":"0","num_feature":"30","num_nodes":"3","size_leaf_vector":"0"}},{"base_weights":[-9.176507E-2],"categories":[],"categories_nodes":[],"categories_segments":[],"categories_sizes":[],"default_left":[0],"id":59,"left_children":[-1],"loss_changes":[0E0],"parents":[2147483647],"right_children":[-1],"split_conditions":[-4.5882533E-3],"split_indices":[0],"split_type":[0],"sum_hessian":[2.043757E1],"tree_param":{"num_deleted":"0","num_feature":"30","num_nodes":"1","size_leaf_vector":"0"}},{"base_weights":[-3.752767E-2],"categories":[],"categories_nodes":[],"categories_segments":[],"categories_sizes":[],"default_left":[0],"id":60,"left_children":[-1],"loss_changes":[0E0],"parents":[2147483647],"right_children":[-1],"split_conditions":[-1.8763834E-3],"split_indices":[0],"split_type":[0],"sum_hessian":[2.1410034E1],"tree_param":{"num_deleted":"0","num_feature":"30","num_nodes":"1","size_leaf_vector":"0"}},{"base_weights":[-4.5473095E-2],"categories":[],"categories_nodes":[],"categories_segments":[],"categories_sizes":[],"default_left":[0],"id":61,"left_children":[-1],"loss_changes":[0E0],"parents":[2147483647],"right_children":[-1],"split_conditions":[-2.2736548E-3],"split_indices":[0],"split_type":[0],"sum_hessian":[2.0811634E1],"tree_param":{"num_deleted":"0","num_feature":"30","num_nodes":"1","size_leaf_vector":"0"}},{"base_weights":[-4.2735092E-2],"categories":[],"categories_nodes":[],"categories_segments":[],"categories_sizes":[],"default_left":[0],"id":62,"left_children":[-1],"loss_changes":[0E0],"parents":[2147483647],"right_children":[-1],"split_conditions":[-2.1367546E-3],"split_indices":[0],"split_type":[0],"sum_hessian":[2.098497E1],"tree_param":{"num_deleted":"0","num_feature":"30","num_nodes":"1","size_leaf_vector":"0"}},{"base_weights":[-1.2218964E-2],"categories":[],"categories_nodes":[],"categories_segments":[],"categories_sizes":[],"default_left":[0],"id":63,"left_children":[-1],"loss_changes":[0E0],"parents":[2147483647],"right_children":[-1],"split_conditions":[-6.1094825E-4],"split_indices":[0],"split_type":[0],"sum_hessian":[2.1096262E1],"tree_param":{"num_deleted":"0","num_feature":"30","num_nodes":"1","size_leaf_vector":"0"}},{"base_weights":[-5.0606113E-2],"categories":[],"categories_nodes":[],"categories_segments":[],"categories_sizes":[],"default_left":[0],"id":64,"left_children":[-1],"loss_changes":[0E0],"parents":[2147483647],"right_children":[-1],"split_conditions":[-2.5303056E-3],"split_indices":[0],"split_type":[0],"sum_hessian":[2.1443024E1],"tree_param":{"num_deleted":"0","num_feature":"30","num_nodes":"1","size_leaf_vector":"0"}},{"base_weights":[-3.7711542E-2],"categories":[],"categories_nodes":[],"categories_segments":[],"categories_sizes":[],"default_left":[0],"id":65,"left_children":[-1],"loss_changes":[0E0],"parents":[2147483647],"right_children":[-1],"split_conditions":[-1.8855771E-3],"split_indices":[0],"split_type":[0],"sum_hessian":[2.1220182E1],"tree_param":{"num_deleted":"0","num_feature":"30","num_nodes":"1","size_leaf_vector":"0"}},{"base_weights":[-4.536297E-2],"categories":[],"categories_nodes":[],"categories_segments":[],"categories_sizes":[],"default_left":[0],"id":66,"left_children":[-1],"loss_changes":[0E0],"parents":[2147483647],"right_children":[-1],"split_conditions":[-2.2681486E-3],"split_indices":[0],"split_type":[0],"sum_hessian":[2.0927843E1],"tree_param":{"num_deleted":"0","num_feature":"30","num_nodes":"1","size_leaf_vector":"0"}},{"base_weights":[-1.0730922E-2],"categories":[],"categories_nodes":[],"categories_segments":[],"categories_sizes":[],"default_left":[0],"id":67,"left_children":[-1],"loss_changes":[0E0],"parents":[2147483647],"right_children":[-1],"split_conditions":[-5.365461E-4],"split_indices":[0],"split_type":[0],"sum_hessian":[2.091944E1],"tree_param":{"num_deleted":"0","num_feature":"30","num_nodes":"1","size_leaf_vector":"0"}},{"base_weights":[-3.1847354E-2],"categories":[],"categories_nodes":[],"categories_segments":[],"categories_sizes":[],"default_left":[0],"id":68,"left_children":[-1],"loss_changes":[0E0],"parents":[2147483647],"right_children":[-1],"split_conditions":[-1.5923678E-3],"split_indices":[0],"split_type":[0],"sum_hessian":[2.1819286E1],"tree_param":{"num_deleted":"0","num_feature":"30","num_nodes":"1","size_leaf_vector":"0"}},{"base_weights":[-3.9189555E-2],"categories":[],"categories_nodes":[],"categories_segments":[],"categories_sizes":[],"default_left":[0],"id":69,"left_children":[-1],"loss_changes":[0E0],"parents":[2147483647],"right_children":[-1],"split_conditions":[-1.9594778E-3],"split_indices":[0],"split_type":[0],"sum_hessian":[2.1054155E1],"tree_param":{"num_deleted":"0","num_feature":"30","num_nodes":"1","size_leaf_vector":"0"}},{"base_weights":[-2.634496E-2],"categories":[],"categories_nodes":[],"categories_segments":[],"categories_sizes":[],"default_left":[0],"id":70,"left_children":[-1],"loss_changes":[0E0],"parents":[2147483647],"right_children":[-1],"split_conditions":[-1.3172481E-3],"split_indices":[0],"split_type":[0],"sum_hessian":[2.0326387E1],"tree_param":{"num_deleted":"0","num_feature":"30","num_nodes":"1","size_leaf_vector":"0"}},{"base_weights":[-5.3250294E-2],"categories":[],"categories_nodes":[],"categories_segments":[],"categories_sizes":[],"default_left":[0],"id":71,"left_children":[-1],"loss_changes":[0E0],"parents":[2147483647],"right_children":[-1],"split_conditions":[-2.6625148E-3],"split_indices":[0],"split_type":[0],"sum_hessian":[2.0327095E1],"tree_param":{"num_deleted":"0","num_feature":"30","num_nodes":"1","size_leaf_vector":"0"}},{"base_weights":[-1.1543277E-2],"categories":[],"categories_nodes":[],"categories_segments":[],"categories_sizes":[],"default_left":[0],"id":72,"left_children":[-1],"loss_changes":[0E0],"parents":[2147483647],"right_children":[-1],"split_conditions":[-5.771638E-4],"split_indices":[0],"split_type":[0],"sum_hessian":[2.18838E1],"tree_param":{"num_deleted":"0","num_feature":"30","num_nodes":"1","size_leaf_vector":"0"}},{"base_weights":[-6.0742993E-2],"categories":[],"categories_nodes":[],"categories_segments":[],"categories_sizes":[],"default_left":[0],"id":73,"left_children":[-1],"loss_changes":[0E0],"parents":[2147483647],"right_children":[-1],"split_conditions":[-3.0371498E-3],"split_indices":[0],"split_type":[0],"sum_hessian":[2.150027E1],"tree_param":{"num_deleted":"0","num_feature":"30","num_nodes":"1","size_leaf_vector":"0"}},{"base_weights":[-2.0525608E-2],"categories":[],"categories_nodes":[],"categories_segments":[],"categories_sizes":[],"default_left":[0],"id":74,"left_children":[-1],"loss_changes":[0E0],"parents":[2147483647],"right_children":[-1],"split_conditions":[-1.0262805E-3],"split_indices":[0],"split_type":[0],"sum_hessian":[2.035172E1],"tree_param":{"num_deleted":"0","num_feature":"30","num_nodes":"1","size_leaf_vector":"0"}},{"base_weights":[-2.7202612E-2],"categories":[],"categories_nodes":[],"categories_segments":[],"categories_sizes":[],"default_left":[0],"id":75,"left_children":[-1],"loss_changes":[0E0],"parents":[2147483647],"right_children":[-1],"split_conditions":[-1.3601306E-3],"split_indices":[0],"split_type":[0],"sum_hessian":[2.0958931E1],"tree_param":{"num_deleted":"0","num_feature":"30","num_nodes":"1","size_leaf_vector":"0"}},{"base_weights":[-1.5526194E-2],"categories":[],"categories_nodes":[],"categories_segments":[],"categories_sizes":[],"default_left":[0],"id":76,"left_children":[-1],"loss_changes":[0E0],"parents":[2147483647],"right_children":[-1],"split_conditions":[-7.763097E-4],"split_indices":[0],"split_type":[0],"sum_hessian":[2.1260288E1],"tree_param":{"num_deleted":"0","num_feature":"30","num_nodes":"1","size_leaf_vector":"0"}},{"base_weights":[-6.1092903E-3],"categories":[],"categories_nodes":[],"categories_segments":[],"categories_sizes":[],"default_left":[0],"id":77,"left_children":[-1],"loss_changes":[0E0],"parents":[2147483647],"right_children":[-1],"split_conditions":[-3.0546452E-4],"split_indices":[0],"split_type":[0],"sum_hessian":[2.0400253E1],"tree_param":{"num_deleted":"0","num_feature":"30","num_nodes":"1","size_leaf_vector":"0"}},{"base_weights":[-5.4034658E-2],"categories":[],"categories_nodes":[],"categories_segments":[],"categories_sizes":[],"default_left":[0],"id":78,"left_children":[-1],"loss_changes":[0E0],"parents":[2147483647],"right_children":[-1],"split_conditions":[-2.701733E-3],"split_indices":[0],"split_type":[0],"sum_hessian":[2.04801E1],"tree_param":{"num_deleted":"0","num_feature":"30","num_nodes":"1","size_leaf_vector":"0"}},{"base_weights":[-2.1057006E-2],"categories":[],"categories_nodes":[],"categories_segments":[],"categories_sizes":[],"default_left":[0],"id":79,"left_children":[-1],"loss_changes":[0E0],"parents":[2147483647],"right_children":[-1],"split_conditions":[-1.0528503E-3],"split_indices":[0],"split_type":[0],"sum_hessian":[2.0599457E1],"tree_param":{"num_deleted":"0","num_feature":"30","num_nodes":"1","size_leaf_vector":"0"}},{"base_weights":[-4.0078275E-2],"categories":[],"categories_nodes":[],"categories_segments":[],"categories_sizes":[],"default_left":[0],"id":80,"left_children":[-1],"loss_changes":[0E0],"parents":[2147483647],"right_children":[-1],"split_conditions":[-2.0039137E-3],"split_indices":[0],"split_type":[0],"sum_hessian":[2.0742384E1],"tree_param":{"num_deleted":"0","num_feature":"30","num_nodes":"1","size_leaf_vector":"0"}},{"base_weights":[-5.0936104E-3],"categories":[],"categories_nodes":[],"categories_segments":[],"categories_sizes":[],"default_left":[0],"id":81,"left_children":[-1],"loss_changes":[0E0],"parents":[2147483647],"right_children":[-1],"split_conditions":[-2.5468052E-4],"split_indices":[0],"split_type":[0],"sum_hessian":[2.151907E1],"tree_param":{"num_deleted":"0","num_feature":"30","num_nodes":"1","size_leaf_vector":"0"}},{"base_weights":[-2.3907848E-2],"categories":[],"categories_nodes":[],"categories_segments":[],"categories_sizes":[],"default_left":[0],"id":82,"left_children":[-1],"loss_changes":[0E0],"parents":[2147483647],"right_children":[-1],"split_conditions":[-1.1953925E-3],"split_indices":[0],"split_type":[0],"sum_hessian":[2.136395E1],"tree_param":{"num_deleted":"0","num_feature":"30","num_nodes":"1","size_leaf_vector":"0"}},{"base_weights":[-2.5546558E-2],"categories":[],"categories_nodes":[],"categories_segments":[],"categories_sizes":[],"default_left":[0],"id":83,"left_children":[-1],"loss_changes":[0E0],"parents":[2147483647],"right_children":[-1],"split_conditions":[-1.2773279E-3],"split_indices":[0],"split_type":[0],"sum_hessian":[2.1147142E1],"tree_param":{"num_deleted":"0","num_feature":"30","num_nodes":"1","size_leaf_vector":"0"}},{"base_weights":[-2.8732158E-2],"categories":[],"categories_nodes":[],"categories_segments":[],"categories_sizes":[],"default_left":[0],"id":84,"left_children":[-1],"loss_changes":[0E0],"parents":[2147483647],"right_children":[-1],"split_conditions":[-1.4366079E-3],"split_indices":[0],"split_type":[0],"sum_hessian":[2.072627E1],"tree_param":{"num_deleted":"0","num_feature":"30","num_nodes":"1","size_leaf_vector":"0"}},{"base_weights":[2.8829858E-2],"categories":[],"categories_nodes":[],"categories_segments":[],"categories_sizes":[],"default_left":[0],"id":85,"left_children":[-1],"loss_changes":[0E0],"parents":[2147483647],"right_children":[-1],"split_conditions":[1.4414929E-3],"split_indices":[0],"split_type":[0],"sum_hessian":[2.1057007E1],"tree_param":{"num_deleted":"0","num_feature":"30","num_nodes":"1","size_leaf_vector":"0"}},{"base_weights":[1.6070394E-2],"categories":[],"categories_nodes":[],"categories_segments":[],"categories_sizes":[],"default_left":[0],"id":86,"left_children":[-1],"loss_changes":[0E0],"parents":[2147483647],"right_children":[-1],"split_conditions":[8.035197E-4],"split_indices":[0],"split_type":[0],"sum_hessian":[2.0820534E1],"tree_param":{"num_deleted":"0","num_feature":"30","num_nodes":"1","size_leaf_vector":"0"}},{"base_weights":[-2.2641113E-3],"categories":[],"categories_nodes":[],"categories_segments":[],"categories_sizes":[],"default_left":[0],"id":87,"left_children":[-1],"loss_changes":[0E0],"parents":[2147483647],"right_children":[-1],"split_conditions":[-1.1320557E-4],"split_indices":[0],"split_type":[0],"sum_hessian":[2.068844E1],"tree_param":{"num_deleted":"0","num_feature":"30","num_nodes":"1","size_leaf_vector":"0"}},{"base_weights":[-2.3821356E-2],"categories":[],"categories_nodes":[],"categories_segments":[],"categories_sizes":[],"default_left":[0],"id":88,"left_children":[-1],"loss_changes":[0E0],"parents":[2147483647],"right_children":[-1],"split_conditions":[-1.1910679E-3],"split_indices":[0],"split_type":[0],"sum_hessian":[2.0189196E1],"tree_param":{"num_deleted":"0","num_feature":"30","num_nodes":"1","size_leaf_vector":"0"}},{"base_weights":[-2.807852E-2],"categories":[],"categories_nodes":[],"categories_segments":[],"categories_sizes":[],"default_left":[0],"id":89,"left_children":[-1],"loss_changes":[0E0],"parents":[2147483647],"right_children":[-1],"split_conditions":[-1.403926E-3],"split_indices":[0],"split_type":[0],"sum_hessian":[2.0169298E1],"tree_param":{"num_deleted":"0","num_feature":"30","num_nodes":"1","size_leaf_vector":"0"}},{"base_weights":[-4.7513667E-2],"categories":[],"categories_nodes":[],"categories_segments":[],"categories_sizes":[],"default_left":[0],"id":90,"left_children":[-1],"loss_changes":[0E0],"parents":[2147483647],"right_children":[-1],"split_conditions":[-2.3756835E-3],"split_indices":[0],"split_type":[0],"sum_hessian":[2.1093382E1],"tree_param":{"num_deleted":"0","num_feature":"30","num_nodes":"1","size_leaf_vector":"0"}},{"base_weights":[-3.6848973E-2],"categories":[],"categories_nodes":[],"categories_segments":[],"categories_sizes":[],"default_left":[0],"id":91,"left_children":[-1],"loss_changes":[0E0],"parents":[2147483647],"right_children":[-1],"split_conditions":[-1.8424487E-3],"split_indices":[0],"split_type":[0],"sum_hessian":[2.0513264E1],"tree_param":{"num_deleted":"0","num_feature":"30","num_nodes":"1","size_leaf_vector":"0"}},{"base_weights":[-2.949125E-2],"categories":[],"categories_nodes":[],"categories_segments":[],"categories_sizes":[],"default_left":[0],"id":92,"left_children":[-1],"loss_changes":[0E0],"parents":[2147483647],"right_children":[-1],"split_conditions":[-1.4745625E-3],"split_indices":[0],"split_type":[0],"sum_hessian":[2.1364588E1],"tree_param":{"num_deleted":"0","num_feature":"30","num_nodes":"1","size_leaf_vector":"0"}},{"base_weights":[-2.9427303E-2],"categories":[],"categories_nodes":[],"categories_segments":[],"categories_sizes":[],"default_left":[0],"id":93,"left_children":[-1],"loss_changes":[0E0],"parents":[2147483647],"right_children":[-1],"split_conditions":[-1.4713652E-3],"split_indices":[0],"split_type":[0],"sum_hessian":[2.1389347E1],"tree_param":{"num_deleted":"0","num_feature":"30","num_nodes":"1","size_leaf_vector":"0"}},{"base_weights":[6.5951245E-3],"categories":[],"categories_nodes":[],"categories_segments":[],"categories_sizes":[],"default_left":[0],"id":94,"left_children":[-1],"loss_changes":[0E0],"parents":[2147483647],"right_children":[-1],"split_conditions":[3.2975624E-4],"split_indices":[0],"split_type":[0],"sum_hessian":[2.1110952E1],"tree_param":{"num_deleted":"0","num_feature":"30","num_nodes":"1","size_leaf_vector":"0"}},{"base_weights":[-1.8114498E-2],"categories":[],"categories_nodes":[],"categories_segments":[],"categories_sizes":[],"default_left":[0],"id":95,"left_children":[-1],"loss_changes":[0E0],"parents":[2147483647],"right_children":[-1],"split_conditions":[-9.057249E-4],"split_indices":[0],"split_type":[0],"sum_hessian":[2.0732067E1],"tree_param":{"num_deleted":"0","num_feature":"30","num_nodes":"1","size_leaf_vector":"0"}},{"base_weights":[-4.7064554E-2],"categories":[],"categories_nodes":[],"categories_segments":[],"categories_sizes":[],"default_left":[0],"id":96,"left_children":[-1],"loss_changes":[0E0],"parents":[2147483647],"right_children":[-1],"split_conditions":[-2.3532277E-3],"split_indices":[0],"split_type":[0],"sum_hessian":[2.1134768E1],"tree_param":{"num_deleted":"0","num_feature":"30","num_nodes":"1","size_leaf_vector":"0"}},{"base_weights":[5.3114495E-3],"categories":[],"categories_nodes":[],"categories_segments":[],"categories_sizes":[],"default_left":[0],"id":97,"left_children":[-1],"loss_changes":[0E0],"parents":[2147483647],"right_children":[-1],"split_conditions":[2.6557248E-4],"split_indices":[0],"split_type":[0],"sum_hessian":[2.07145E1],"tree_param":{"num_deleted":"0","num_feature":"30","num_nodes":"1","size_leaf_vector":"0"}},{"base_weights":[-2.9642846E-2],"categories":[],"categories_nodes":[],"categories_segments":[],"categories_sizes":[],"default_left":[0],"id":98,"left_children":[-1],"loss_changes":[0E0],"parents":[2147483647],"right_children":[-1],"split_conditions":[-1.4821424E-3],"split_indices":[0],"split_type":[0],"sum_hessian":[2.1143528E1],"tree_param":{"num_deleted":"0","num_feature":"30","num_nodes":"1","size_leaf_vector":"0"}},{"base_weights":[6.8947924E-3],"categories":[],"categories_nodes":[],"categories_segments":[],"categories_sizes":[],"default_left":[0],"id":99,"left_children":[-1],"loss_changes":[0E0],"parents":[2147483647],"right_children":[-1],"split_conditions":[3.4473962E-4],"split_indices":[0],"split_type":[0],"sum_hessian":[2.0808226E1],"tree_param":{"num_deleted":"0","num_feature":"30","num_nodes":"1","size_leaf_vector":"0"}}]},"name":"gbtree"},"learner_model_param":{"base_score":"5E-1","num_class":"0","num_feature":"30","num_target":"1"},"objective":{"name":"binary:logistic","reg_loss_param":{"scale_pos_weight":"1"}}},"version":[1,6,2]}